README.md
setup.py
authlib_database/__init__.py
authlib_database.egg-info/PKG-INFO
authlib_database.egg-info/SOURCES.txt
authlib_database.egg-info/dependency_links.txt
authlib_database.egg-info/requires.txt
authlib_database.egg-info/top_level.txt
authlib_database/oauth2/__init__.py
authlib_database/oauth2/mongoengine.py
authlib_database/oauth2/pony.py