Metadata-Version: 1.0
Name: authlib-database
Version: 0.1.0
Summary: Support for third-party databases in the Autlib library.
Home-page: https://github.com/kyzima-spb/authlib-database
Author: Kirill Vercetti
Author-email: office@kyzima-spb.com
License: GNU AGPLv3+
Platform: UNKNOWN
